s3explorer/main.py
s3explorer-0.0.1.dist-info/METADATA
s3explorer-0.0.1.dist-info/WHEEL
s3explorer-0.0.1.dist-info/entry_points.txt
s3explorer-0.0.1.dist-info/licenses/LICENSE
s3explorer-0.0.1.dist-info/RECORD
