Metadata-Version: 2.4
Name: S3Explorer
Version: 0.0.1
Summary: A simple but effective terminal based interface (TUI) for S3.
Project-URL: Homepage, https://github.com/MHaz42/s3explorer
Project-URL: Issues, https://github.com/MHaz42/s3explorer/issues
Author-email: Bouchet Matéo <mateo.bouchet@mhaz42.fr>, Conde Cyril <cyril.conde@gmail.com>
License-Expression: GPL-3.0-or-later
License-File: LICENSE
Requires-Dist: textual
